{
    "_links": {
        "self": {
            "href": "http:\/\/default\/sites\/default\/files\/2019-02\/Graph%20background.jpg"
        },
        "type": {
            "href": "http:\/\/drupal.org\/rest\/type\/file\/file"
        },
        "http:\/\/drupal.org\/rest\/relation\/file\/file\/uid": [
            {
                "href": "http:\/\/default\/user\/1?_format=hal_json"
            }
        ]
    },
    "fid": [
        {
            "value": 31
        }
    ],
    "uuid": [
        {
            "value": "af6d2da7-a054-4ef3-9f9f-c2afe1894b83"
        }
    ],
    "langcode": [
        {
            "value": "en"
        }
    ],
    "_embedded": {
        "http:\/\/drupal.org\/rest\/relation\/file\/file\/uid": [
            {
                "_links": {
                    "self": {
                        "href": "http:\/\/default\/user\/1?_format=hal_json"
                    },
                    "type": {
                        "href": "http:\/\/drupal.org\/rest\/type\/user\/user"
                    }
                },
                "uuid": [
                    {
                        "value": "a17ff604-b133-4ba0-82fa-96404fbcda46"
                    }
                ]
            }
        ]
    },
    "filename": [
        {
            "value": "Graph background.jpg"
        }
    ],
    "uri": [
        {
            "value": "public:\/\/2019-02\/Graph background.jpg",
            "url": "\/sites\/default\/files\/2019-02\/Graph%20background.jpg"
        }
    ],
    "filemime": [
        {
            "value": "image\/jpeg"
        }
    ],
    "filesize": [
        {
            "value": 786278
        }
    ],
    "status": [
        {
            "value": true
        }
    ],
    "created": [
        {
            "value": "2019-02-07T05:15:35+00:00",
            "format": "Y-m-d\\TH:i:sP"
        }
    ],
    "changed": [
        {
            "value": "2019-02-07T05:16:40+00:00",
            "format": "Y-m-d\\TH:i:sP"
        }
    ]
}